[{"genre": "научная фантастика", "book-title": "Бухта Эсмеральда", "author": "Артур Конан Дойл", "pages": "253", "year": "1987", "isbn": "724-7299770587", "description": "middle", "img_url": "https://upload.booook.ru/303373.png", "rating": "3.5", "views": 60554}, {"genre": "научная фантастика", "book-title": "Слепота", "author": "Иван Тургенев", "pages": "400", "year": "1905", "isbn": "619-2363037854", "description": "write it yourself", "img_url": "https://upload.abc-book.it/686724.svg", "rating": "3.2", "views": 5259}, {"genre": "научная фантастика", "book-title": "Великий Гэтсби", "author": "Габриэль Гарсиа Маркес", "pages": "498", "year": "1976", "isbn": "349-3460558590", "description": "Описаниеdescription", "img_url": "https://upload.buybook.org/814928.jpeg", "rating": "0.9", "views": 49448}, {"genre": "научная фантастика", "book-title": "Страх и отвращение в Лас-Вегасе", "author": "Герберт Уэллс", "pages": "263", "year": "1803", "isbn": "547-8360051768", "description": "Описаниеwrite it yourself", "img_url": "https://upload.freebook.xyz/932349.jpg", "rating": "4.3", "views": 86040}, {"genre": "научная фантастика", "book-title": "Слепота", "author": "Генрих Сенкевич", "pages": "296", "year": "1959", "isbn": "476-7639680202", "description": "description", "img_url": "https://upload.buybook.org/159838.jpeg", "rating": "3.7", "views": 12229}, {"genre": "научная фантастика", "book-title": "Сумерки", "author": "Казуо Исигуро", "pages": "302", "year": "1821", "isbn": "167-4061400234", "description": "Описаниеdescription", "img_url": "https://upload.book.com/522394.svg", "rating": "1.2", "views": 12517}, {"genre": "научная фантастика", "book-title": "Заводной апельсин", "author": "Сигрид Унсет", "pages": "478", "year": "1813", "isbn": "838-4029725320", "description": "Описаниеwrite it yourself", "img_url": "https://upload.buybook.org/880228.svg", "rating": "1.6", "views": 72736}, {"genre": "научная фантастика", "book-title": "Старик и море", "author": "Владимир Набоков", "pages": "404", "year": "1928", "isbn": "740-7987865194", "description": "Описаниеvery impressive", "img_url": "https://upload.booook.ru/218939.png", "rating": "3.6", "views": 25648}, {"genre": "научная фантастика", "book-title": "Белый шум", "author": "Эрнест Хемингуэй", "pages": "444", "year": "1885", "isbn": "321-7840396834", "description": "small", "img_url": "https://upload.booook.ru/27323.png", "rating": "1.6", "views": 96909}, {"genre": "научная фантастика", "book-title": "Американские горки", "author": "Ярослав Гашек", "pages": "496", "year": "1819", "isbn": "254-2305565665", "description": "small", "img_url": "https://upload.freebook.xyz/958161.webp", "rating": "1.2", "views": 30789}, {"genre": "научная фантастика", "book-title": "Ребекка", "author": "Александр Пушкин", "pages": "145", "year": "1930", "isbn": "729-4044101409", "description": "write it yourself", "img_url": "https://upload.buybook.org/734331.jpg", "rating": "5.0", "views": 69350}, {"genre": "научная фантастика", "book-title": "Божество реки", "author": "Ярослав Гашек", "pages": "402", "year": "1984", "isbn": "345-6025094695", "description": "Описаниеdescription", "img_url": "https://upload.booook.ru/568139.webp", "rating": "3.2", "views": 16252}, {"genre": "научная фантастика", "book-title": "Дюна", "author": "Умберто Эко", "pages": "401", "year": "1870", "isbn": "821-7015561268", "description": "Описаниеsmall", "img_url": "https://upload.book.com/446662.jpg", "rating": "0.1", "views": 85578}, {"genre": "научная фантастика", "book-title": "Портрет Дориана Грея", "author": "Харпер Ли", "pages": "137", "year": "1812", "isbn": "873-7125752960", "description": "write it yourself", "img_url": "https://upload.freebook.xyz/161759.svg", "rating": "2.6", "views": 6247}, {"genre": "научная фантастика", "book-title": "Лолита", "author": "Эрих Мария Ремарк", "pages": "361", "year": "1992", "isbn": "302-8933402550", "description": "middle", "img_url": "https://upload.booook.ru/195225.jpg", "rating": "2.2", "views": 47869}, {"genre": "научная фантастика", "book-title": "Дюна", "author": "Джон Фаулз", "pages": "156", "year": "1826", "isbn": "821-2143777857", "description": "Описаниеwrite it yourself", "img_url": "https://upload.freebook.xyz/862280.webp", "rating": "3.5", "views": 52000}, {"genre": "научная фантастика", "book-title": "Повелитель мух", "author": "Харуки Мураками", "pages": "320", "year": "1943", "isbn": "337-9047598603", "description": "small", "img_url": "https://upload.abc-book.it/921047.jpeg", "rating": "0.4", "views": 8514}, {"genre": "научная фантастика", "book-title": "Оно", "author": "Станислав Лем", "pages": "228", "year": "1846", "isbn": "147-6453020072", "description": "Описаниеsmall", "img_url": "https://upload.abc-book.it/829607.jpg", "rating": "1.6", "views": 31117}, {"genre": "научная фантастика", "book-title": "Трудно быть богом", "author": "Станислав Лем", "pages": "254", "year": "1821", "isbn": "527-6014072474", "description": "Описаниеmiddle", "img_url": "https://upload.booook.ru/760773.jpg", "rating": "0.1", "views": 37386}, {"genre": "научная фантастика", "book-title": "Война и мир", "author": "Джозеф Конрад", "pages": "332", "year": "1822", "isbn": "960-6940698031", "description": "Описаниеsmall", "img_url": "https://upload.freebook.xyz/285562.jpeg", "rating": "2.1", "views": 5580}, {"genre": "научная фантастика", "book-title": "Убить пересмешника", "author": "Станислав Лем", "pages": "262", "year": "2010", "isbn": "121-3402922757", "description": "Описаниеwrite it yourself", "img_url": "https://upload.book.com/579171.png", "rating": "0.6", "views": 70457}, {"genre": "научная фантастика", "book-title": "Божество реки", "author": "Джозеф Конрад", "pages": "462", "year": "1841", "isbn": "656-1760668064", "description": "Описаниеvery impressive", "img_url": "https://upload.freebook.xyz/86285.jpeg", "rating": "2.3", "views": 86185}, {"genre": "научная фантастика", "book-title": "Великий Гэтсби", "author": "Тед Хьюз", "pages": "227", "year": "2015", "isbn": "750-4898960429", "description": "description", "img_url": "https://upload.abc-book.it/675617.png", "rating": "0.8", "views": 29522}, {"genre": "научная фантастика", "book-title": "Осиная фабрика", "author": "Иван Тургенев", "pages": "436", "year": "1801", "isbn": "894-3648364174", "description": "Описаниеdescription", "img_url": "https://upload.abc-book.it/656994.webp", "rating": "3.9", "views": 27027}, {"genre": "научная фантастика", "book-title": "Мертвые души", "author": "Синклер Льюис", "pages": "357", "year": "1975", "isbn": "725-7158206187", "description": "write it yourself", "img_url": "https://upload.booook.ru/496655.svg", "rating": "3.3", "views": 66069}, {"genre": "научная фантастика", "book-title": "Ватек", "author": "Иэн Бэнкс", "pages": "457", "year": "1990", "isbn": "532-9963446564", "description": "Описаниеsmall", "img_url": "https://upload.book.com/829560.jpeg", "rating": "0.7", "views": 60700}, {"genre": "научная фантастика", "book-title": "Имя розы", "author": "Сельма Лагерлёф", "pages": "453", "year": "1902", "isbn": "937-2496001295", "description": "middle", "img_url": "https://upload.buybook.org/350334.webp", "rating": "3.2", "views": 22786}, {"genre": "научная фантастика", "book-title": "Звездная пыль", "author": "Колин Маккалоу", "pages": "241", "year": "1957", "isbn": "742-2317267217", "description": "Описаниеmiddle", "img_url": "https://upload.freebook.xyz/488959.svg", "rating": "2.0", "views": 5958}, {"genre": "научная фантастика", "book-title": "Трудно быть богом", "author": "Фрэнсис Скотт Фицджеральд", "pages": "455", "year": "1841", "isbn": "881-1396150201", "description": "write it yourself", "img_url": "https://upload.freebook.xyz/800417.webp", "rating": "3.9", "views": 83551}, {"genre": "научная фантастика", "book-title": "Твин Пикс: Воспоминания специального агента ФБР Дейла Купера", "author": "Лев Толстой", "pages": "317", "year": "1966", "isbn": "965-1636860626", "description": "description", "img_url": "https://upload.abc-book.it/795185.jpg", "rating": "3.9", "views": 59987}, {"genre": "научная фантастика", "book-title": "Планета обезьян", "author": "Эрих Мария Ремарк", "pages": "464", "year": "1819", "isbn": "436-6170274393", "description": "Описаниеvery impressive", "img_url": "https://upload.abc-book.it/653019.png", "rating": "2.8", "views": 98532}, {"genre": "научная фантастика", "book-title": "Гордость и предубеждение", "author": "Харуки Мураками", "pages": "313", "year": "1809", "isbn": "648-8818240669", "description": "Описаниеsmall", "img_url": "https://upload.book.com/692903.jpg", "rating": "3.0", "views": 59622}, {"genre": "научная фантастика", "book-title": "Волхв", "author": "Исаак Бабель", "pages": "359", "year": "1908", "isbn": "793-9405243145", "description": "Описаниеsmall", "img_url": "https://upload.booook.ru/66590.jpeg", "rating": "5.0", "views": 23896}, {"genre": "научная фантастика", "book-title": "Портрет Дориана Грея", "author": "Дж. Р. Р. Толкин", "pages": "321", "year": "1921", "isbn": "977-4578712437", "description": "Описаниеwrite it yourself", "img_url": "https://upload.freebook.xyz/84069.webp", "rating": "2.0", "views": 59922}, {"genre": "научная фантастика", "book-title": "Божество реки", "author": "Колин Маккалоу", "pages": "374", "year": "1873", "isbn": "317-1969184692", "description": "description", "img_url": "https://upload.book.com/356202.svg", "rating": "0.5", "views": 23671}, {"genre": "научная фантастика", "book-title": "Колыбель для кошки", "author": "Сигрид Унсет", "pages": "167", "year": "1931", "isbn": "896-6113367579", "description": "very impressive", "img_url": "https://upload.freebook.xyz/788006.png", "rating": "0.1", "views": 27854}, {"genre": "научная фантастика", "book-title": "Франкенштейн", "author": "Роберт Льюис Стивенсон", "pages": "199", "year": "1856", "isbn": "982-4705106194", "description": "Описаниеwrite it yourself", "img_url": "https://upload.buybook.org/217141.webp", "rating": "3.6", "views": 68285}, {"genre": "научная фантастика", "book-title": "Война и мир", "author": "Клайв Стейплз Льюис", "pages": "354", "year": "1952", "isbn": "629-9454594569", "description": "Описаниеwrite it yourself", "img_url": "https://upload.abc-book.it/372277.jpeg", "rating": "0.1", "views": 15118}, {"genre": "научная фантастика", "book-title": "Великий Гэтсби", "author": "Джон Фаулз", "pages": "249", "year": "1889", "isbn": "703-9843889272", "description": "Описаниеwrite it yourself", "img_url": "https://upload.freebook.xyz/437990.svg", "rating": "4.2", "views": 67787}, {"genre": "научная фантастика", "book-title": "Большие надежды", "author": "Синклер Льюис", "pages": "154", "year": "1946", "isbn": "551-4996863183", "description": "description", "img_url": "https://upload.freebook.xyz/829316.svg", "rating": "1.5", "views": 91587}, {"genre": "научная фантастика", "book-title": "Женщина в песках", "author": "Станислав Лем", "pages": "369", "year": "1935", "isbn": "252-7554646367", "description": "Описаниеwrite it yourself", "img_url": "https://upload.book.com/145262.jpeg", "rating": "2.1", "views": 65709}, {"genre": "научная фантастика", "book-title": "Убить пересмешника", "author": "Оскар Уайльд", "pages": "426", "year": "1971", "isbn": "806-7708911000", "description": "Описаниеsmall", "img_url": "https://upload.booook.ru/537640.jpg", "rating": "0.8", "views": 48118}, {"genre": "научная фантастика", "book-title": "Город призраков", "author": "Патрик Зюскинд", "pages": "354", "year": "2014", "isbn": "763-7089370420", "description": "write it yourself", "img_url": "https://upload.abc-book.it/153308.png", "rating": "3.8", "views": 4896}, {"genre": "научная фантастика", "book-title": "Фауст", "author": "Лев Толстой", "pages": "162", "year": "1897", "isbn": "338-1376343810", "description": "very impressive", "img_url": "https://upload.abc-book.it/162228.webp", "rating": "1.0", "views": 41938}, {"genre": "научная фантастика", "book-title": "Страх и отвращение в Лас-Вегасе", "author": "Стивен Кинг", "pages": "344", "year": "1853", "isbn": "887-5714533279", "description": "Описаниеmiddle", "img_url": "https://upload.buybook.org/999616.webp", "rating": "2.4", "views": 92839}, {"genre": "научная фантастика", "book-title": "Темная башня", "author": "Джордж Оруэлл", "pages": "224", "year": "1874", "isbn": "457-3116070128", "description": "small", "img_url": "https://upload.freebook.xyz/167480.jpg", "rating": "4.3", "views": 80761}, {"genre": "научная фантастика", "book-title": "Повелитель мух", "author": "Клайв Стейплз Льюис", "pages": "345", "year": "2006", "isbn": "252-7887010250", "description": "Описаниеsmall", "img_url": "https://upload.abc-book.it/209830.png", "rating": "0.3", "views": 14337}, {"genre": "научная фантастика", "book-title": "20 000 лье под водой", "author": "Исаак Бабель", "pages": "323", "year": "1900", "isbn": "390-8310755577", "description": "write it yourself", "img_url": "https://upload.freebook.xyz/806059.svg", "rating": "1.4", "views": 920}, {"genre": "научная фантастика", "book-title": "Осиная фабрика", "author": "Синклер Льюис", "pages": "329", "year": "1884", "isbn": "374-5939435053", "description": "write it yourself", "img_url": "https://upload.freebook.xyz/888699.jpeg", "rating": "4.4", "views": 98716}, {"genre": "научная фантастика", "book-title": "Лолита", "author": "Стивен Кинг", "pages": "445", "year": "1889", "isbn": "741-3277739705", "description": "very impressive", "img_url": "https://upload.freebook.xyz/210860.svg", "rating": "4.0", "views": 48670}, {"genre": "научная фантастика", "book-title": "По направлению к сваолу", "author": "Борис Пастернак", "pages": "247", "year": "1944", "isbn": "134-1538302268", "description": "write it yourself", "img_url": "https://upload.freebook.xyz/161605.webp", "rating": "3.1", "views": 51153}, {"genre": "научная фантастика", "book-title": "Слепота", "author": "Лев Толстой", "pages": "144", "year": "1988", "isbn": "996-4643551555", "description": "Описаниеvery impressive", "img_url": "https://upload.book.com/524256.png", "rating": "2.9", "views": 10578}, {"genre": "научная фантастика", "book-title": "Автостопом по галактике", "author": "Роберт Льюис Стивенсон", "pages": "271", "year": "1904", "isbn": "930-8346492199", "description": "Описаниеdescription", "img_url": "https://upload.buybook.org/940548.webp", "rating": "4.7", "views": 89891}, {"genre": "научная фантастика", "book-title": "Исчезнувшая", "author": "Синклер Льюис", "pages": "419", "year": "1998", "isbn": "627-3269787629", "description": "middle", "img_url": "https://upload.book.com/258462.png", "rating": "2.1", "views": 31588}, {"genre": "научная фантастика", "book-title": "Алхимик", "author": "Роберт Льюис Стивенсон", "pages": "470", "year": "1802", "isbn": "854-5963253877", "description": "Описаниеsmall", "img_url": "https://upload.book.com/804775.webp", "rating": "3.6", "views": 22270}, {"genre": "научная фантастика", "book-title": "Мастер и Маргарита", "author": "Владимир Набоков", "pages": "450", "year": "1938", "isbn": "290-9997493137", "description": "middle", "img_url": "https://upload.abc-book.it/897917.jpeg", "rating": "2.3", "views": 25527}, {"genre": "научная фантастика", "book-title": "Плавучий трава", "author": "Федор Достоевский", "pages": "289", "year": "1941", "isbn": "452-1029957006", "description": "Описаниеvery impressive", "img_url": "https://upload.buybook.org/395963.png", "rating": "1.0", "views": 17970}, {"genre": "научная фантастика", "book-title": "Оно", "author": "Джек Лондон", "pages": "208", "year": "1882", "isbn": "359-6979929518", "description": "Описаниеwrite it yourself", "img_url": "https://upload.book.com/162622.jpeg", "rating": "0.2", "views": 67743}, {"genre": "научная фантастика", "book-title": "Свет в лесу", "author": "Джон Фаулз", "pages": "146", "year": "1849", "isbn": "513-6595015088", "description": "Описаниеsmall", "img_url": "https://upload.book.com/757739.svg", "rating": "0.5", "views": 86236}, {"genre": "научная фантастика", "book-title": "Ребекка", "author": "Иэн Бэнкс", "pages": "141", "year": "1858", "isbn": "648-6481804737", "description": "Описаниеsmall", "img_url": "https://upload.buybook.org/620523.jpg", "rating": "4.6", "views": 49600}, {"genre": "научная фантастика", "book-title": "Сквозь время", "author": "Алан Александр Милн", "pages": "338", "year": "1948", "isbn": "954-2764037406", "description": "Описаниеmiddle", "img_url": "https://upload.book.com/744589.png", "rating": "2.2", "views": 31460}, {"genre": "научная фантастика", "book-title": "Бесконечная история", "author": "Эрнест Хемингуэй", "pages": "309", "year": "1935", "isbn": "525-3088998749", "description": "Описаниеsmall", "img_url": "https://upload.booook.ru/211528.webp", "rating": "3.5", "views": 64091}, {"genre": "научная фантастика", "book-title": "Плавучий трава", "author": "Антон Чехов", "pages": "348", "year": "1927", "isbn": "895-8396254684", "description": "Описаниеwrite it yourself", "img_url": "https://upload.abc-book.it/342856.jpg", "rating": "0.6", "views": 21445}, {"genre": "научная фантастика", "book-title": "Оно", "author": "Джордж Оруэлл", "pages": "347", "year": "1834", "isbn": "626-7220467903", "description": "Описаниеmiddle", "img_url": "https://upload.book.com/599700.webp", "rating": "4.8", "views": 52974}, {"genre": "научная фантастика", "book-title": "Неукротимый", "author": "Патрик Зюскинд", "pages": "205", "year": "1922", "isbn": "830-1732910122", "description": "Описаниеwrite it yourself", "img_url": "https://upload.buybook.org/829224.svg", "rating": "1.5", "views": 24168}, {"genre": "научная фантастика", "book-title": "Вещие сестрички", "author": "Патрик Зюскинд", "pages": "428", "year": "1901", "isbn": "877-9548305613", "description": "Описаниеmiddle", "img_url": "https://upload.buybook.org/96979.png", "rating": "1.6", "views": 14351}, {"genre": "научная фантастика", "book-title": "Алхимик", "author": "Казуо Исигуро", "pages": "479", "year": "1852", "isbn": "323-1529296902", "description": "Описаниеdescription", "img_url": "https://upload.book.com/605813.svg", "rating": "3.4", "views": 56847}, {"genre": "научная фантастика", "book-title": "Колыбель для кошки", "author": "Николай Гоголь", "pages": "409", "year": "2009", "isbn": "583-8599805952", "description": "very impressive", "img_url": "https://upload.freebook.xyz/347462.svg", "rating": "2.5", "views": 19094}, {"genre": "научная фантастика", "book-title": "Под стеклянным колпаком", "author": "Оскар Уайльд", "pages": "107", "year": "1865", "isbn": "967-9472851142", "description": "middle", "img_url": "https://upload.book.com/235583.png", "rating": "1.5", "views": 36176}, {"genre": "научная фантастика", "book-title": "Франкенштейн", "author": "Джозеф Конрад", "pages": "396", "year": "1901", "isbn": "499-9786344255", "description": "description", "img_url": "https://upload.abc-book.it/796964.webp", "rating": "1.4", "views": 78568}, {"genre": "научная фантастика", "book-title": "Сквозь время", "author": "Эрнест Хемингуэй", "pages": "188", "year": "1875", "isbn": "651-2905249359", "description": "write it yourself", "img_url": "https://upload.abc-book.it/570190.jpg", "rating": "2.8", "views": 84433}, {"genre": "научная фантастика", "book-title": "Колыбель для кошки", "author": "Николай Гоголь", "pages": "482", "year": "1997", "isbn": "829-9942511214", "description": "middle", "img_url": "https://upload.abc-book.it/484035.png", "rating": "0.3", "views": 82989}, {"genre": "научная фантастика", "book-title": "451 градус по Фаренгейту", "author": "Джон Фаулз", "pages": "196", "year": "1969", "isbn": "607-1793816788", "description": "Описаниеvery impressive", "img_url": "https://upload.booook.ru/662139.webp", "rating": "0.3", "views": 30539}, {"genre": "научная фантастика", "book-title": "Недовольство культурой", "author": "Борис Пастернак", "pages": "352", "year": "1896", "isbn": "868-3896099953", "description": "small", "img_url": "https://upload.freebook.xyz/244234.webp", "rating": "2.1", "views": 38147}, {"genre": "научная фантастика", "book-title": "Кандида", "author": "Оскар Уайльд", "pages": "215", "year": "1956", "isbn": "626-2266203848", "description": "very impressive", "img_url": "https://upload.freebook.xyz/30391.jpg", "rating": "4.2", "views": 97845}, {"genre": "научная фантастика", "book-title": "Трудно быть богом", "author": "Тед Хьюз", "pages": "184", "year": "1940", "isbn": "604-7993876742", "description": "Описаниеdescription", "img_url": "https://upload.buybook.org/378575.svg", "rating": "4.0", "views": 58527}, {"genre": "научная фантастика", "book-title": "Молот ведьм", "author": "Оскар Уайльд", "pages": "474", "year": "2012", "isbn": "267-9054582453", "description": "Описаниеwrite it yourself", "img_url": "https://upload.freebook.xyz/462839.svg", "rating": "2.5", "views": 78977}, {"genre": "научная фантастика", "book-title": "О дивный новый мир", "author": "Тед Хьюз", "pages": "381", "year": "1857", "isbn": "393-2701759936", "description": "Описаниеdescription", "img_url": "https://upload.abc-book.it/480772.jpeg", "rating": "2.2", "views": 53386}, {"genre": "научная фантастика", "book-title": "Идиот", "author": "Алексей Толстой", "pages": "266", "year": "1982", "isbn": "235-3874279273", "description": "Описаниеsmall", "img_url": "https://upload.booook.ru/712085.jpg", "rating": "0.3", "views": 74987}, {"genre": "научная фантастика", "book-title": "Молот ведьм", "author": "Ярослав Гашек", "pages": "320", "year": "2015", "isbn": "293-4572264389", "description": "write it yourself", "img_url": "https://upload.booook.ru/561192.png", "rating": "1.7", "views": 20629}, {"genre": "научная фантастика", "book-title": "Возвращение в Брайдсхед", "author": "Габриэль Гарсиа Маркес", "pages": "319", "year": "1872", "isbn": "641-1027756346", "description": "write it yourself", "img_url": "https://upload.buybook.org/889431.webp", "rating": "0.6", "views": 32916}, {"genre": "научная фантастика", "book-title": "Под стеклянным колпаком", "author": "Габриэль Гарсиа Маркес", "pages": "129", "year": "1919", "isbn": "998-9343423120", "description": "write it yourself", "img_url": "https://upload.freebook.xyz/5507.svg", "rating": "1.9", "views": 69016}, {"genre": "научная фантастика", "book-title": "Гордость и предубеждение", "author": "Джозеф Конрад", "pages": "487", "year": "1991", "isbn": "533-4898127299", "description": "middle", "img_url": "https://upload.booook.ru/752458.webp", "rating": "4.9", "views": 49006}, {"genre": "научная фантастика", "book-title": "Белый шум", "author": "Джордж Оруэлл", "pages": "458", "year": "1895", "isbn": "669-6361430234", "description": "Описаниеdescription", "img_url": "https://upload.book.com/648011.jpeg", "rating": "4.1", "views": 17715}, {"genre": "научная фантастика", "book-title": "Гроздья гнева", "author": "Эрих Мария Ремарк", "pages": "453", "year": "2005", "isbn": "221-1110428497", "description": "write it yourself", "img_url": "https://upload.abc-book.it/165703.jpg", "rating": "0.6", "views": 93074}, {"genre": "научная фантастика", "book-title": "Черный дом", "author": "Александр Пушкин", "pages": "279", "year": "1941", "isbn": "800-7085969628", "description": "Описаниеmiddle", "img_url": "https://upload.freebook.xyz/956172.webp", "rating": "1.8", "views": 91855}, {"genre": "научная фантастика", "book-title": "1984", "author": "Николай Гоголь", "pages": "144", "year": "1923", "isbn": "677-5523153936", "description": "write it yourself", "img_url": "https://upload.buybook.org/923344.png", "rating": "0.9", "views": 90639}, {"genre": "научная фантастика", "book-title": "Под стеклянным колпаком", "author": "Юстейн Гордер", "pages": "252", "year": "1888", "isbn": "193-1267848706", "description": "write it yourself", "img_url": "https://upload.book.com/420261.jpeg", "rating": "1.0", "views": 66747}, {"genre": "научная фантастика", "book-title": "Американские горки", "author": "Джозеф Конрад", "pages": "136", "year": "2007", "isbn": "925-6545586725", "description": "Описаниеwrite it yourself", "img_url": "https://upload.freebook.xyz/428860.webp", "rating": "2.0", "views": 46596}, {"genre": "научная фантастика", "book-title": "Белый шум", "author": "Синклер Льюис", "pages": "337", "year": "1821", "isbn": "539-8755414274", "description": "Описаниеsmall", "img_url": "https://upload.freebook.xyz/213373.webp", "rating": "2.7", "views": 86059}, {"genre": "научная фантастика", "book-title": "О дивный новый мир", "author": "Иэн Бэнкс", "pages": "108", "year": "1871", "isbn": "950-3681475234", "description": "Описаниеsmall", "img_url": "https://upload.abc-book.it/476114.jpeg", "rating": "4.6", "views": 47562}, {"genre": "научная фантастика", "book-title": "Колыбель для кошки", "author": "Салман Рушди", "pages": "199", "year": "1865", "isbn": "616-6903139416", "description": "Описаниеwrite it yourself", "img_url": "https://upload.buybook.org/287848.jpg", "rating": "1.3", "views": 69563}, {"genre": "научная фантастика", "book-title": "Ярмарка тщеславия", "author": "Жюль Верн", "pages": "287", "year": "1872", "isbn": "380-1978493483", "description": "Описаниеmiddle", "img_url": "https://upload.freebook.xyz/222345.png", "rating": "1.2", "views": 75919}, {"genre": "научная фантастика", "book-title": "Имя розы", "author": "Фрэнсис Скотт Фицджеральд", "pages": "202", "year": "1842", "isbn": "207-2973643907", "description": "very impressive", "img_url": "https://upload.booook.ru/573173.png", "rating": "2.9", "views": 58746}, {"genre": "научная фантастика", "book-title": "Лолита", "author": "Исаак Бабель", "pages": "431", "year": "1895", "isbn": "650-2131441468", "description": "middle", "img_url": "https://upload.freebook.xyz/80418.webp", "rating": "0.2", "views": 39735}, {"genre": "научная фантастика", "book-title": "Сто лет одиночества", "author": "Фрэнсис Скотт Фицджеральд", "pages": "305", "year": "1940", "isbn": "904-9506158608", "description": "Описаниеsmall", "img_url": "https://upload.buybook.org/792876.jpeg", "rating": "0.4", "views": 78228}, {"genre": "научная фантастика", "book-title": "Божество реки", "author": "Джозеф Конрад", "pages": "340", "year": "1839", "isbn": "736-8028304025", "description": "middle", "img_url": "https://upload.freebook.xyz/134142.webp", "rating": "2.7", "views": 37294}, {"genre": "научная фантастика", "book-title": "Прощай, оружие", "author": "Харуки Мураками", "pages": "338", "year": "1870", "isbn": "464-3662786310", "description": "Описаниеdescription", "img_url": "https://upload.booook.ru/57556.jpg", "rating": "2.1", "views": 78051}, {"genre": "научная фантастика", "book-title": "1984", "author": "Казуо Исигуро", "pages": "421", "year": "1982", "isbn": "643-5944669971", "description": "Описаниеdescription", "img_url": "https://upload.book.com/743096.png", "rating": "3.0", "views": 89788}, {"genre": "научная фантастика", "book-title": "Скотный двор", "author": "Клайв Стейплз Льюис", "pages": "385", "year": "2002", "isbn": "693-3498498026", "description": "Описаниеdescription", "img_url": "https://upload.book.com/420331.jpg", "rating": "0.3", "views": 97481}, {"genre": "научная фантастика", "book-title": "Портрет Дориана Грея", "author": "Роберт Льюис Стивенсон", "pages": "255", "year": "1893", "isbn": "154-6135337230", "description": "very impressive", "img_url": "https://upload.booook.ru/263169.jpg", "rating": "0.7", "views": 24828}, {"genre": "научная фантастика", "book-title": "Падение дома Ашеров", "author": "Иэн Бэнкс", "pages": "476", "year": "1881", "isbn": "609-9466783166", "description": "write it yourself", "img_url": "https://upload.abc-book.it/724079.webp", "rating": "1.7", "views": 57462}, {"genre": "научная фантастика", "book-title": "Сумерки", "author": "Эрнест Хемингуэй", "pages": "368", "year": "1849", "isbn": "980-6675470715", "description": "Описаниеsmall", "img_url": "https://upload.abc-book.it/309318.webp", "rating": "4.2", "views": 9477}, {"genre": "научная фантастика", "book-title": "В дороге", "author": "Фрэнсис Скотт Фицджеральд", "pages": "363", "year": "1884", "isbn": "618-9001726697", "description": "Описаниеdescription", "img_url": "https://upload.freebook.xyz/342083.jpeg", "rating": "0.6", "views": 24813}, {"genre": "научная фантастика", "book-title": "Ватек", "author": "Эрих Мария Ремарк", "pages": "370", "year": "1947", "isbn": "226-9667739923", "description": "small", "img_url": "https://upload.book.com/779351.webp", "rating": "1.4", "views": 65187}, {"genre": "научная фантастика", "book-title": "Большие надежды", "author": "Дж. Р. Р. Толкин", "pages": "247", "year": "1842", "isbn": "978-6555402481", "description": "middle", "img_url": "https://upload.abc-book.it/178900.jpeg", "rating": "3.6", "views": 56402}, {"genre": "научная фантастика", "book-title": "Имя розы", "author": "Иэн Бэнкс", "pages": "292", "year": "1880", "isbn": "520-8808679805", "description": "Описаниеvery impressive", "img_url": "https://upload.buybook.org/288227.png", "rating": "2.5", "views": 96162}, {"genre": "научная фантастика", "book-title": "Идиот", "author": "Артур Конан Дойл", "pages": "243", "year": "2001", "isbn": "264-6679501619", "description": "small", "img_url": "https://upload.book.com/221814.jpeg", "rating": "0.8", "views": 60328}, {"genre": "научная фантастика", "book-title": "Неукротимый", "author": "Федор Достоевский", "pages": "135", "year": "1839", "isbn": "812-5136373731", "description": "very impressive", "img_url": "https://upload.freebook.xyz/332978.webp", "rating": "2.9", "views": 52397}, {"genre": "научная фантастика", "book-title": "Недовольство культурой", "author": "Джордж Оруэлл", "pages": "223", "year": "1939", "isbn": "983-3359020455", "description": "middle", "img_url": "https://upload.abc-book.it/39079.jpeg", "rating": "3.0", "views": 31459}, {"genre": "научная фантастика", "book-title": "Черный дом", "author": "Колин Маккалоу", "pages": "148", "year": "1857", "isbn": "662-6991668752", "description": "middle", "img_url": "https://upload.booook.ru/187420.png", "rating": "4.0", "views": 61100}, {"genre": "научная фантастика", "book-title": "Бойня номер пять, или Крестовый поход детей", "author": "Исаак Бабель", "pages": "447", "year": "2012", "isbn": "121-5673226465", "description": "Описаниеmiddle", "img_url": "https://upload.abc-book.it/117164.jpeg", "rating": "1.4", "views": 99917}, {"genre": "научная фантастика", "book-title": "Падение дома Ашеров", "author": "Уильям Голдинг", "pages": "208", "year": "1943", "isbn": "620-5651106022", "description": "write it yourself", "img_url": "https://upload.freebook.xyz/992847.png", "rating": "4.2", "views": 88035}, {"genre": "научная фантастика", "book-title": "Идиот", "author": "Артур Конан Дойл", "pages": "417", "year": "1896", "isbn": "301-2926657967", "description": "Описаниеdescription", "img_url": "https://upload.abc-book.it/311774.jpg", "rating": "3.2", "views": 51278}, {"genre": "научная фантастика", "book-title": "Бухта Эсмеральда", "author": "Федор Достоевский", "pages": "435", "year": "1811", "isbn": "167-2345249730", "description": "Описаниеdescription", "img_url": "https://upload.buybook.org/756247.jpg", "rating": "0.5", "views": 1374}, {"genre": "научная фантастика", "book-title": "В дороге", "author": "Иван Тургенев", "pages": "227", "year": "1926", "isbn": "530-5477388731", "description": "very impressive", "img_url": "https://upload.booook.ru/100253.svg", "rating": "0.5", "views": 4169}, {"genre": "научная фантастика", "book-title": "Человек-невидимка", "author": "Лев Толстой", "pages": "302", "year": "1823", "isbn": "833-4138465779", "description": "description", "img_url": "https://upload.book.com/145702.webp", "rating": "0.6", "views": 127}, {"genre": "научная фантастика", "book-title": "Вещие сестрички", "author": "Федор Достоевский", "pages": "267", "year": "1845", "isbn": "800-1803612193", "description": "Описаниеsmall", "img_url": "https://upload.buybook.org/533851.png", "rating": "4.6", "views": 6717}, {"genre": "научная фантастика", "book-title": "Черный дом", "author": "Джордж Оруэлл", "pages": "303", "year": "2005", "isbn": "534-3208340009", "description": "description", "img_url": "https://upload.freebook.xyz/92669.jpg", "rating": "3.5", "views": 64351}, {"genre": "научная фантастика", "book-title": "Приключения Гекльберри Финна", "author": "Дон Делилло", "pages": "488", "year": "1931", "isbn": "700-7158568517", "description": "write it yourself", "img_url": "https://upload.booook.ru/136190.png", "rating": "2.6", "views": 58640}, {"genre": "научная фантастика", "book-title": "Гарри Поттер и Философский камень", "author": "Николай Гоголь", "pages": "314", "year": "1889", "isbn": "703-6980641724", "description": "very impressive", "img_url": "https://upload.freebook.xyz/348010.jpg", "rating": "5.0", "views": 13899}]